CHANGES.rst
COPYRIGHT
LICENSE
MANIFEST.in
README.rst
setup.cfg
setup.py
tox.ini
dropafile/__init__.py
dropafile/openssl.conf
dropafile.egg-info/PKG-INFO
dropafile.egg-info/SOURCES.txt
dropafile.egg-info/dependency_links.txt
dropafile.egg-info/entry_points.txt
dropafile.egg-info/namespace_packages.txt
dropafile.egg-info/not-zip-safe
dropafile.egg-info/requires.txt
dropafile.egg-info/top_level.txt
dropafile/static/dropzone.css
dropafile/static/dropzone.js
dropafile/static/page.html
dropafile/static/style.css